src/__init__.py
src/cli.py
promptizethis-0.0.2.dist-info/LICENSE
promptizethis-0.0.2.dist-info/METADATA
promptizethis-0.0.2.dist-info/WHEEL
promptizethis-0.0.2.dist-info/entry_points.txt
promptizethis-0.0.2.dist-info/top_level.txt
promptizethis-0.0.2.dist-info/RECORD
