Metadata-Version: 2.1
Name: promptizethis
Version: 0.0.2
Summary: Interactive GUI to generate prompts from codebase files.
Home-page: https://github.com/ChesterAiGo/PromptizeThis
Author: Chester Wang
Author-email: freeaigo2012@gmail.com
Classifier: Programming Language :: Python :: 3
Classifier: License :: OSI Approved :: MIT License
Classifier: Operating System :: OS Independent
Requires-Python: >=3.7
License-File: LICENSE
